chunkwrap/__init__.py
chunkwrap/chunking.py
chunkwrap/cli.py
chunkwrap/config.py
chunkwrap/core.py
chunkwrap/file_handler.py
chunkwrap/output.py
chunkwrap/security.py
chunkwrap/state.py
chunkwrap/utils.py
chunkwrap-2.4.1.dist-info/licenses/LICENSE
chunkwrap-2.4.1.dist-info/METADATA
chunkwrap-2.4.1.dist-info/WHEEL
chunkwrap-2.4.1.dist-info/entry_points.txt
chunkwrap-2.4.1.dist-info/top_level.txt
chunkwrap-2.4.1.dist-info/RECORD
