Metadata-Version: 2.4
Name: chunkwrap
Version: 2.4.1
Summary: Command-line tool to select code/docs for LLMs with secret masking and a hard cap on final output size.
Author-email: Ian Ellis <ellisiana@gmail.com>
License:                     GNU GENERAL PUBLIC LICENSE
Project-URL: Homepage, https://github.com/magicalbob/chunkwrap/wiki
Project-URL: Repository, https://github.com/magicalbob/chunkwrap
Project-URL: Issues, https://github.com/magicalbob/chunkwrap/issues
Project-URL: Changelog, https://github.com/magicalbob/chunkwrap/releases
Keywords: cli,chunking,secret-masking,json,clipboard,context-window,token-budget,chatgpt,openai,claude,anthropic,gemini,perplexity,copilot
Classifier: Development Status :: 4 - Beta
Classifier: Environment :: Console
Classifier: Intended Audience :: Developers
Classifier: Programming Language :: Python :: 3
Classifier: Programming Language :: Python :: 3.9
Classifier: Programming Language :: Python :: 3.10
Classifier: Programming Language :: Python :: 3.11
Classifier: Programming Language :: Python :: 3.12
Classifier: Operating System :: OS Independent
Classifier: Topic :: Software Development :: Build Tools
Classifier: Topic :: Utilities
Requires-Python: >=3.9
License-File: LICENSE
Requires-Dist: pyperclip>=1.9.0
Provides-Extra: dev
Requires-Dist: build>=1.2.2.post1; extra == "dev"
Requires-Dist: pytest>=6.0.0; extra == "dev"
Requires-Dist: pytest-mock>=3.14.1; extra == "dev"
Requires-Dist: pytest-cov>=2.0.0; extra == "dev"
Requires-Dist: black>=22.0.0; extra == "dev"
Requires-Dist: flake8>=4.0.0; extra == "dev"
Requires-Dist: mypy>=0.910; extra == "dev"
Requires-Dist: twine>=6.1.0; extra == "dev"
Dynamic: license-file
